build/lib/build/lib/kajgg/__init__.py
build/lib/build/lib/kajgg/bot.py
build/lib/build/lib/kajgg/client.py
build/lib/build/lib/kajgg/context.py
build/lib/build/lib/kajgg/dispatcher.py
build/lib/build/lib/kajgg/gateway.py
build/lib/build/lib/kajgg/logging.py
build/lib/build/lib/kajgg/_gen/__init__.py
build/lib/build/lib/kajgg/_gen/events/__init__.py
build/lib/build/lib/kajgg/_gen/events/author_updated.py
build/lib/build/lib/kajgg/_gen/events/channel_created.py
build/lib/build/lib/kajgg/_gen/events/channel_deleted.py
build/lib/build/lib/kajgg/_gen/events/channel_updated.py
build/lib/build/lib/kajgg/_gen/events/event.py
build/lib/build/lib/kajgg/_gen/events/event_type.py
build/lib/build/lib/kajgg/_gen/events/message_created.py
build/lib/build/lib/kajgg/_gen/events/message_deleted.py
build/lib/build/lib/kajgg/_gen/events/message_updated.py
build/lib/build/lib/kajgg/_gen/events/typing_started.py
build/lib/build/lib/kajgg/_gen/models/__init__.py
build/lib/build/lib/kajgg/_gen/models/author.py
build/lib/build/lib/kajgg/_gen/models/channel.py
build/lib/build/lib/kajgg/_gen/models/embed.py
build/lib/build/lib/kajgg/_gen/models/emoji.py
build/lib/build/lib/kajgg/_gen/models/file.py
build/lib/build/lib/kajgg/_gen/models/file_upload.py
build/lib/build/lib/kajgg/_gen/models/flags.py
build/lib/build/lib/kajgg/_gen/models/message.py
build/lib/build/lib/kajgg/_gen/models/message_type.py
build/lib/build/lib/kajgg/_gen/models/status.py
build/lib/build/lib/kajgg/_gen/models/user.py
build/lib/build/lib/kajgg/_gen/models/webhook.py
build/lib/build/lib/kajgg/_internal/__init__.py
build/lib/build/lib/kajgg/_internal/convert.py
build/lib/build/lib/kajgg/events/__init__.py
build/lib/build/lib/kajgg/models/__init__.py
build/lib/kajgg/__init__.py
build/lib/kajgg/bot.py
build/lib/kajgg/client.py
build/lib/kajgg/context.py
build/lib/kajgg/dispatcher.py
build/lib/kajgg/gateway.py
build/lib/kajgg/logging.py
build/lib/kajgg/_gen/__init__.py
build/lib/kajgg/_gen/events/__init__.py
kajgg_chatlib-0.1.0.dist-info/METADATA
kajgg_chatlib-0.1.0.dist-info/WHEEL
kajgg_chatlib-0.1.0.dist-info/top_level.txt
kajgg_chatlib-0.1.0.dist-info/RECORD
